mylib_054/__init__.py
mylib_054-0.1.dist-info/LICENSE.txt
mylib_054-0.1.dist-info/METADATA
mylib_054-0.1.dist-info/WHEEL
mylib_054-0.1.dist-info/top_level.txt
mylib_054-0.1.dist-info/RECORD
