Metadata-Version: 2.1
Name: mylib-054
Version: 0.1
Summary: for calculating cube
Author: Yash Rasam
Author-email: yashrasam@gmail.com
Classifier: Programming Language :: Python :: 3
Classifier: License :: OSI Approved :: MIT License
Classifier: Operating System :: OS Independent
License-File: LICENSE.txt
